Simple_Logger_Tool/Simple_Logger_Tool.py
Simple_Logger_Tool/__init__.py
Simple_Logger_Tool-1.0.5.dist-info/LICENSE
Simple_Logger_Tool-1.0.5.dist-info/METADATA
Simple_Logger_Tool-1.0.5.dist-info/WHEEL
Simple_Logger_Tool-1.0.5.dist-info/top_level.txt
Simple_Logger_Tool-1.0.5.dist-info/RECORD
