Metadata-Version: 2.1
Name: Simple-Logger-Tool
Version: 1.0.5
Summary: Just some simple logging functions that can be used in pretty much any program.
Home-page: https://github.com/m-inwards/Simple-Logging
Author: Matt Inwards
Author-email: 
License: UNKNOWN
Platform: UNKNOWN
Classifier: Programming Language :: Python :: 3
Classifier: License :: OSI Approved :: MIT License
License-File: LICENSE
